ssz/__init__.py
ssz/abc.py
ssz/codec.py
ssz/constants.py
ssz/exceptions.py
ssz/hash.py
ssz/hash_tree.py
ssz/hashable_container.py
ssz/hashable_list.py
ssz/hashable_structure.py
ssz/hashable_vector.py
ssz/py.typed
ssz/tree_hash.py
ssz/typing.py
ssz/utils.py
ssz/cache/__init__.py
ssz/cache/cache.py
ssz/cache/utils.py
ssz/sedes/__init__.py
ssz/sedes/base.py
ssz/sedes/basic.py
ssz/sedes/bitlist.py
ssz/sedes/bitvector.py
ssz/sedes/boolean.py
ssz/sedes/byte.py
ssz/sedes/byte_list.py
ssz/sedes/byte_vector.py
ssz/sedes/container.py
ssz/sedes/list.py
ssz/sedes/serializable.py
ssz/sedes/signed_serializable.py
ssz/sedes/uint.py
ssz/sedes/vector.py
ssz/tools/__init__.py
ssz/tools/codec.py
ssz/tools/dump.py
ssz/tools/parse.py
ssz-0.5.2.dist-info/LICENSE
ssz-0.5.2.dist-info/METADATA
ssz-0.5.2.dist-info/WHEEL
ssz-0.5.2.dist-info/top_level.txt
ssz-0.5.2.dist-info/RECORD
